README.md
setup.cfg
setup.py
gree/__init__.py
gree/aes_cipher.py
gree/consts.py
gree/exceptions.py
gree/gree_config.py
gree/gree_device.py
gree.egg-info/PKG-INFO
gree.egg-info/SOURCES.txt
gree.egg-info/dependency_links.txt
gree.egg-info/not-zip-safe
gree.egg-info/requires.txt
gree.egg-info/top_level.txt